{"assets":{"263533AE3C29C0261D86F1C7013C5D9C":{"type":"texture","index":0,"url":{"native":"assets\/02715B29-62EF-416D-A489-87F4BA993075.pdf"},"width":1920,"height":1080},"C3E2EC46ECF16EED03A997890ACB918D":{"type":"texture","index":2,"url":{"native":"assets\/02715B29-62EF-416D-A489-87F4BA993075.pdf"},"width":1920,"height":1080},"FE30FE1BEA9165A050126B8F2140D362":{"type":"texture","index":1,"url":{"native":"assets\/02715B29-62EF-416D-A489-87F4BA993075.pdf"},"width":1920,"height":1080}},"events":[{"effects":[{"beginTime":0,"baseLayer":{"animations":[],"initialState":{"affineTransform":[1,0,0,1,0,0],"masksToBounds":false,"rotation":0,"scale":1,"position":{"pointX":960,"pointY":540},"width":1920,"sublayerTransform":[1,0,0,0,0,1,0,0,0,0,1,0,0,0,0,1],"contentsRect":{"y":0,"x":0,"width":1,"height":1},"opacity":1,"edgeAntialiasingMask":251658240,"height":1080,"hidden":false,"anchorPoint":{"pointX":0.5,"pointY":0.5}},"objectID":"0","layers":[{"animations":[],"initialState":{"affineTransform":[1,0,0,1,0,0],"masksToBounds":false,"rotation":0,"scale":1,"position":{"pointX":960,"pointY":540},"width":1920,"sublayerTransform":[1,0,0,0,0,1,0,0,0,0,1,-0.00035007912466775983,0,0,0,1],"contentsRect":{"y":0,"x":0,"width":1,"height":1},"opacity":1,"edgeAntialiasingMask":251658240,"height":1080,"hidden":false,"anchorPoint":{"pointX":0.5,"pointY":0.5}},"layers":[{"animations":[],"layers":[],"texturedRectangle":{"isBackgroundTexture":false,"singleTextureOpacity":1,"textureType":0,"textBaseline":0,"textXHeight":0,"isVerticalText":false},"initialState":{"affineTransform":[1,0,0,1,0,0],"masksToBounds":false,"rotation":0,"scale":1,"position":{"pointX":960,"pointY":540},"width":1920,"sublayerTransform":[1,0,0,0,0,1,0,0,0,0,1,0,0,0,0,1],"contentsRect":{"y":0,"x":0,"width":1,"height":1},"opacity":1,"edgeAntialiasingMask":0,"height":1080,"hidden":false,"anchorPoint":{"pointX":0.5,"pointY":0.5}},"texture":"FE30FE1BEA9165A050126B8F2140D362"},{"animations":[{"additive":false,"timeOffset":0,"beginTime":0,"from":{"scalar":false},"repeatCount":0,"fillMode":"both","duration":0.001,"autoreverses":false,"property":"hidden","to":{"scalar":true},"removedOnCompletion":false}],"layers":[],"texturedRectangle":{"isBackgroundTexture":false,"singleTextureOpacity":1,"textureType":0,"textBaseline":0,"textXHeight":0,"isVerticalText":false},"initialState":{"affineTransform":[1,0,0,1,0,0],"masksToBounds":false,"rotation":0,"scale":1,"position":{"pointX":960,"pointY":540},"width":1920,"sublayerTransform":[1,0,0,0,0,1,0,0,0,0,1,0,0,0,0,1],"contentsRect":{"y":0,"x":0,"width":1,"height":1},"opacity":1,"edgeAntialiasingMask":0,"height":1080,"hidden":false,"anchorPoint":{"pointX":0.5,"pointY":0.5}},"texture":"263533AE3C29C0261D86F1C7013C5D9C"}]}]},"effects":[],"duration":0.001,"type":"transition","attributes":{"direction":0},"name":"none","objectID":"0"}],"automaticPlay":false,"hyperlinks":[{"url":"https:\/\/www.biblegateway.com\/passage\/?search=Psalm+23:1-4,6&version=ESV","targetRectangle":{"y":70.619542598724365,"x":1616.5594604492187,"width":161.40000000000009,"height":28.3280029296875}},{"url":"?slideid=73527225-8249-497D-A8A8-0535154E6893","events":{"73527225-8249-497D-A8A8-0535154E6893":{"effects":[{"beginTime":0,"baseLayer":{"animations":[],"initialState":{"affineTransform":[1,0,0,1,0,0],"masksToBounds":false,"rotation":0,"scale":1,"position":{"pointX":960,"pointY":540},"width":1920,"sublayerTransform":[1,0,0,0,0,1,0,0,0,0,1,0,0,0,0,1],"contentsRect":{"y":0,"x":0,"width":1,"height":1},"opacity":1,"edgeAntialiasingMask":251658240,"height":1080,"hidden":false,"anchorPoint":{"pointX":0.5,"pointY":0.5}},"objectID":"0","layers":[{"animations":[],"initialState":{"affineTransform":[1,0,0,1,0,0],"masksToBounds":false,"rotation":0,"scale":1,"position":{"pointX":960,"pointY":540},"width":1920,"sublayerTransform":[1,0,0,0,0,1,0,0,0,0,1,-0.00035007912466775983,0,0,0,1],"contentsRect":{"y":0,"x":0,"width":1,"height":1},"opacity":1,"edgeAntialiasingMask":251658240,"height":1080,"hidden":false,"anchorPoint":{"pointX":0.5,"pointY":0.5}},"layers":[{"animations":[],"layers":[],"texturedRectangle":{"isBackgroundTexture":false,"singleTextureOpacity":1,"textureType":0,"textBaseline":0,"textXHeight":0,"isVerticalText":false},"initialState":{"affineTransform":[1,0,0,1,0,0],"masksToBounds":false,"rotation":0,"scale":1,"position":{"pointX":960,"pointY":540},"width":1920,"sublayerTransform":[1,0,0,0,0,1,0,0,0,0,1,0,0,0,0,1],"contentsRect":{"y":0,"x":0,"width":1,"height":1},"opacity":1,"edgeAntialiasingMask":0,"height":1080,"hidden":false,"anchorPoint":{"pointX":0.5,"pointY":0.5}},"texture":"C3E2EC46ECF16EED03A997890ACB918D"},{"animations":[{"additive":false,"timeOffset":0,"beginTime":0,"from":{"scalar":false},"repeatCount":0,"fillMode":"both","duration":0.001,"autoreverses":false,"property":"hidden","to":{"scalar":true},"removedOnCompletion":false}],"layers":[],"texturedRectangle":{"isBackgroundTexture":false,"singleTextureOpacity":1,"textureType":0,"textBaseline":0,"textXHeight":0,"isVerticalText":false},"initialState":{"affineTransform":[1,0,0,1,0,0],"masksToBounds":false,"rotation":0,"scale":1,"position":{"pointX":960,"pointY":540},"width":1920,"sublayerTransform":[1,0,0,0,0,1,0,0,0,0,1,0,0,0,0,1],"contentsRect":{"y":0,"x":0,"width":1,"height":1},"opacity":1,"edgeAntialiasingMask":0,"height":1080,"hidden":false,"anchorPoint":{"pointX":0.5,"pointY":0.5}},"texture":"263533AE3C29C0261D86F1C7013C5D9C"}]}]},"effects":[],"duration":0.001,"type":"transition","attributes":{"direction":0},"name":"none","objectID":"0"}],"automaticPlay":false,"hyperlinks":[],"accessibility":[],"baseLayer":{"animations":[],"initialState":{"affineTransform":[1,0,0,1,0,0],"masksToBounds":false,"rotation":0,"scale":1,"position":{"pointX":960,"pointY":540},"width":1920,"sublayerTransform":[1,0,0,0,0,1,0,0,0,0,1,0,0,0,0,1],"contentsRect":{"y":0,"x":0,"width":1,"height":1},"opacity":1,"edgeAntialiasingMask":251658240,"height":1080,"hidden":false,"anchorPoint":{"pointX":0.5,"pointY":0.5}},"objectID":"0","layers":[{"animations":[],"initialState":{"affineTransform":[1,0,0,1,0,0],"masksToBounds":false,"rotation":0,"scale":1,"position":{"pointX":960,"pointY":540},"width":1920,"sublayerTransform":[1,0,0,0,0,1,0,0,0,0,1,-0.00035007912466775983,0,0,0,1],"contentsRect":{"y":0,"x":0,"width":1,"height":1},"opacity":1,"edgeAntialiasingMask":251658240,"height":1080,"hidden":false,"anchorPoint":{"pointX":0.5,"pointY":0.5}},"layers":[{"animations":[],"layers":[],"texturedRectangle":{"isBackgroundTexture":false,"singleTextureOpacity":1,"textureType":0,"textBaseline":0,"textXHeight":0,"isVerticalText":false},"initialState":{"affineTransform":[1,0,0,1,0,0],"masksToBounds":false,"rotation":0,"scale":1,"position":{"pointX":960,"pointY":540},"width":1920,"sublayerTransform":[1,0,0,0,0,1,0,0,0,0,1,0,0,0,0,1],"contentsRect":{"y":0,"x":0,"width":1,"height":1},"opacity":1,"edgeAntialiasingMask":0,"height":1080,"hidden":false,"anchorPoint":{"pointX":0.5,"pointY":0.5}},"texture":"263533AE3C29C0261D86F1C7013C5D9C"}]}]}}},"targetRectangle":{"y":976.47430419921875,"x":903.4501953125,"width":100,"height":100}},{"url":"https:\/\/audio.com\/stefaniecg\/psalm-23","targetRectangle":{"y":91.423728942871094,"x":920,"width":80.000001192092896,"height":80.000001192092896}},{"url":"?slideid=73527225-8249-497D-A8A8-0535154E6893","events":{"73527225-8249-497D-A8A8-0535154E6893":{"effects":[{"beginTime":0,"baseLayer":{"animations":[],"initialState":{"affineTransform":[1,0,0,1,0,0],"masksToBounds":false,"rotation":0,"scale":1,"position":{"pointX":960,"pointY":540},"width":1920,"sublayerTransform":[1,0,0,0,0,1,0,0,0,0,1,0,0,0,0,1],"contentsRect":{"y":0,"x":0,"width":1,"height":1},"opacity":1,"edgeAntialiasingMask":251658240,"height":1080,"hidden":false,"anchorPoint":{"pointX":0.5,"pointY":0.5}},"objectID":"0","layers":[{"animations":[],"initialState":{"affineTransform":[1,0,0,1,0,0],"masksToBounds":false,"rotation":0,"scale":1,"position":{"pointX":960,"pointY":540},"width":1920,"sublayerTransform":[1,0,0,0,0,1,0,0,0,0,1,-0.00035007912466775983,0,0,0,1],"contentsRect":{"y":0,"x":0,"width":1,"height":1},"opacity":1,"edgeAntialiasingMask":251658240,"height":1080,"hidden":false,"anchorPoint":{"pointX":0.5,"pointY":0.5}},"layers":[{"animations":[],"layers":[],"texturedRectangle":{"isBackgroundTexture":false,"singleTextureOpacity":1,"textureType":0,"textBaseline":0,"textXHeight":0,"isVerticalText":false},"initialState":{"affineTransform":[1,0,0,1,0,0],"masksToBounds":false,"rotation":0,"scale":1,"position":{"pointX":960,"pointY":540},"width":1920,"sublayerTransform":[1,0,0,0,0,1,0,0,0,0,1,0,0,0,0,1],"contentsRect":{"y":0,"x":0,"width":1,"height":1},"opacity":1,"edgeAntialiasingMask":0,"height":1080,"hidden":false,"anchorPoint":{"pointX":0.5,"pointY":0.5}},"texture":"C3E2EC46ECF16EED03A997890ACB918D"},{"animations":[{"additive":false,"timeOffset":0,"beginTime":0,"from":{"scalar":false},"repeatCount":0,"fillMode":"both","duration":0.001,"autoreverses":false,"property":"hidden","to":{"scalar":true},"removedOnCompletion":false}],"layers":[],"texturedRectangle":{"isBackgroundTexture":false,"singleTextureOpacity":1,"textureType":0,"textBaseline":0,"textXHeight":0,"isVerticalText":false},"initialState":{"affineTransform":[1,0,0,1,0,0],"masksToBounds":false,"rotation":0,"scale":1,"position":{"pointX":960,"pointY":540},"width":1920,"sublayerTransform":[1,0,0,0,0,1,0,0,0,0,1,0,0,0,0,1],"contentsRect":{"y":0,"x":0,"width":1,"height":1},"opacity":1,"edgeAntialiasingMask":0,"height":1080,"hidden":false,"anchorPoint":{"pointX":0.5,"pointY":0.5}},"texture":"263533AE3C29C0261D86F1C7013C5D9C"}]}]},"effects":[],"duration":0.001,"type":"transition","attributes":{"direction":0},"name":"none","objectID":"0"}],"automaticPlay":false,"hyperlinks":[],"accessibility":[],"baseLayer":{"animations":[],"initialState":{"affineTransform":[1,0,0,1,0,0],"masksToBounds":false,"rotation":0,"scale":1,"position":{"pointX":960,"pointY":540},"width":1920,"sublayerTransform":[1,0,0,0,0,1,0,0,0,0,1,0,0,0,0,1],"contentsRect":{"y":0,"x":0,"width":1,"height":1},"opacity":1,"edgeAntialiasingMask":251658240,"height":1080,"hidden":false,"anchorPoint":{"pointX":0.5,"pointY":0.5}},"objectID":"0","layers":[{"animations":[],"initialState":{"affineTransform":[1,0,0,1,0,0],"masksToBounds":false,"rotation":0,"scale":1,"position":{"pointX":960,"pointY":540},"width":1920,"sublayerTransform":[1,0,0,0,0,1,0,0,0,0,1,-0.00035007912466775983,0,0,0,1],"contentsRect":{"y":0,"x":0,"width":1,"height":1},"opacity":1,"edgeAntialiasingMask":251658240,"height":1080,"hidden":false,"anchorPoint":{"pointX":0.5,"pointY":0.5}},"layers":[{"animations":[],"layers":[],"texturedRectangle":{"isBackgroundTexture":false,"singleTextureOpacity":1,"textureType":0,"textBaseline":0,"textXHeight":0,"isVerticalText":false},"initialState":{"affineTransform":[1,0,0,1,0,0],"masksToBounds":false,"rotation":0,"scale":1,"position":{"pointX":960,"pointY":540},"width":1920,"sublayerTransform":[1,0,0,0,0,1,0,0,0,0,1,0,0,0,0,1],"contentsRect":{"y":0,"x":0,"width":1,"height":1},"opacity":1,"edgeAntialiasingMask":0,"height":1080,"hidden":false,"anchorPoint":{"pointX":0.5,"pointY":0.5}},"texture":"263533AE3C29C0261D86F1C7013C5D9C"}]}]}}},"targetRectangle":{"y":991.47429509847643,"x":917.5283203125,"width":71.849595849298566,"height":70.000000279254891}}],"accessibility":[{"text":"I-walk","targetRectangle":{"y":706.76474761962891,"x":677.87006133794785,"width":40.259999999999991,"height":16.580001831054688}},{"text":"above","targetRectangle":{"y":689.59806060791016,"x":1711.7758734226227,"width":41.115000000000009,"height":16.580001831054688}},{"text":"YHWH\\u2028(Adonai)","targetRectangle":{"y":538.09806126356125,"x":551.62663340568542,"width":56.995000000000005,"height":33.580001831054688}},{"text":"only","targetRectangle":{"y":424.76474761962891,"x":868.77668714523315,"width":27.779999999999973,"height":16.580001831054688}},{"text":"Scripture reference:","targetRectangle":{"y":41.619542598724365,"x":1591.9114604492188,"width":210.69599999999991,"height":28.3280029296875}},{"text":"Psalm 23:1-4,6","targetRectangle":{"y":70.619542598724365,"x":1616.5594604492187,"width":161.40000000000009,"height":28.3280029296875}},{"text":"and-I-return ","targetRectangle":{"y":529.59806126356125,"x":810.51918681621555,"width":84.464999999999918,"height":16.580001831054688}},{"text":"(turn\/repent)","targetRectangle":{"y":546.59806126356125,"x":809.55168681621547,"width":82.230000000000018,"height":16.580001831054688}},{"text":"in-valley","targetRectangle":{"y":706.76468658447266,"x":543.02918577194214,"width":55.274999999999977,"height":16.580001831054688}},{"text":"water","targetRectangle":{"y":689.59806060791016,"x":1628.3999993801117,"width":37.200000000000045,"height":16.580001831054688}},{"text":"מִזְמ֥וֹר כייג Psalm 23","targetRectangle":{"y":79,"x":99,"width":571.80884819939729,"height":100.53440856933594}},{"text":"in-hause","targetRectangle":{"y":538.09806060791016,"x":669.10256230831146,"width":57.794999999999959,"height":16.580001831054688}},{"text":"darkness","targetRectangle":{"y":706.76468658447266,"x":384.77084267139435,"width":61.125,"height":16.580001831054688}},{"text":"rest-places ","targetRectangle":{"y":689.59806060791016,"x":1473.6349995946885,"width":78.899999999999864,"height":16.580001831054688}},{"text":"me-shepherds","targetRectangle":{"y":429.15549468994141,"x":1539.8383717536926,"width":96.990000000000009,"height":16.580001831054688}},{"text":"[Chorus]","targetRectangle":{"y":286.83523559570312,"x":789.38769471403214,"width":123.89999999999998,"height":58.677875617260725}},{"text":"{x2אַ֤ךְ ט֤וֹב וָחֶ֣סֶד יִ֭רְדְּפוּנִי {כָּל־יְמֵ֣י חַיָּ֑י  וְשַׁבְתִּ֥י בְּבֵית־יְ֝הוָ֗ה {לְאֹ֣רֶךְ יָמִֽים }׃ ","targetRectangle":{"y":345.51311121296385,"x":157.0127728390321,"width":788.73585937500002,"height":223.00000286102295}},{"text":"[B]","targetRectangle":{"y":568.5131140739868,"x":877.19769471403208,"width":36.090000000000032,"height":58.096003035545436}},{"text":" גַּ֤ם כִּֽי־אֵלֵ֨ךְ בְּגֵ֪יא צַלְמָ֡וֶת    ","targetRectangle":{"y":626.60911710953224,"x":316.68124940153211,"width":672.3486328125,"height":131.30000168085098}},{"text":" (x2) לֹא־אִ֘ירָ֤א רָ֗ע\\u2028[Chorus] x1","targetRectangle":{"y":757.90911879038322,"x":528.24238221403209,"width":392.04531250000002,"height":189.97787729811171}},{"text":"[A]","targetRectangle":{"y":286.83523559570312,"x":1721.7201953125,"width":34.980000000000018,"height":57.096003035545436}},{"text":" יְהוָ֥ה רֹ֝עִ֗י לֹ֣א אֶחְסָֽר׃","targetRectangle":{"y":343.93123863124856,"x":1236.2802734375,"width":520.419921875,"height":131.30000168085098}},{"text":" (x2) בִּנְא֣וֹת דֶּ֭שֶׁא יַרְבִּיצֵ֑נִי ","targetRectangle":{"y":475.23124031209954,"x":1189.9753515625,"width":585.66039062499999,"height":131.30000168085098}},{"text":"עַל־מֵ֖י מְנֻח֣וֹת יְנַהֲלֵֽנִי׃","targetRectangle":{"y":606.53124199295053,"x":1239.458984375,"width":517.2412109375,"height":131.30000168085098}},{"text":"(x2) נַפְשִׁ֥י יְשׁוֹבֵ֑ב","targetRectangle":{"y":737.83124367380151,"x":1393.0515234375,"width":363.64867187499999,"height":131.30000168085098}},{"text":"to-length","targetRectangle":{"y":538.09806060791016,"x":409.71496999263763,"width":60.569999999999993,"height":16.580001831054688}},{"text":"4","targetRectangle":{"y":655.70217931270599,"x":954.43994087219244,"width":11.119999999999891,"height":23.44000244140625}},{"text":"not","targetRectangle":{"y":842.09799957275391,"x":871.82918703556061,"width":21.674999999999955,"height":16.580001831054688}},{"text":"He-guides-me","targetRectangle":{"y":689.59806060791016,"x":1286.9325001239777,"width":96.134999999999991,"height":16.580001831054688}},{"text":"no","targetRectangle":{"y":429.15549468994141,"x":1475.1916261315346,"width":16.950000000000045,"height":16.580001831054688}},{"text":"good","targetRectangle":{"y":424.76474761962891,"x":771.23033505678177,"width":34.725000000000023,"height":16.580001831054688}},{"text":"￼","targetRectangle":{"y":1022.4577338695526,"x":1856.1666821769322,"width":20.016000000000076,"height":21.496002197265625}},{"text":"days","targetRectangle":{"y":538.09806060791016,"x":300.13007187843323,"width":31.949999999999989,"height":16.580001831054688}},{"text":"6","targetRectangle":{"y":369.61334264278412,"x":954.44000032544136,"width":11.120000000000005,"height":23.44000244140625}},{"text":"YHWH\\u2028(Adonai)","targetRectangle":{"y":425.6554953455925,"x":1670.9733741283417,"width":56.994999999999891,"height":33.580001831054688}},{"text":"I-fear","targetRectangle":{"y":842.09799957275391,"x":737.03418749570847,"width":35.264999999999986,"height":16.580001831054688}},{"text":"my-soul","targetRectangle":{"y":822.70725250244141,"x":1671.3783727884293,"width":53.910000000000082,"height":16.580001831054688}},{"text":"I-lack","targetRectangle":{"y":429.15549468994141,"x":1329.1941256523132,"width":36.944999999999936,"height":16.580001831054688}},{"text":"and-goodness","targetRectangle":{"y":424.76474761962891,"x":631.30370593070984,"width":97.245000000000005,"height":16.580001831054688}},{"text":"1","targetRectangle":{"y":372.27999913692474,"x":1790.1941507160664,"width":11.119999999999891,"height":23.44000244140625}},{"text":"evil","targetRectangle":{"y":842.09799957275391,"x":615.5591869354248,"width":22.215000000000032,"height":16.580001831054688}},{"text":"He-returns \\u2028(turn\/repent)","targetRectangle":{"y":818.2072531580925,"x":1497.8850004673004,"width":88.119999999999891,"height":33.580001831054688}},{"text":"in-pastures","targetRectangle":{"y":556.48880767822266,"x":1633.3500002622604,"width":75.299999999999955,"height":16.580001831054688}},{"text":"they-pursue-me","targetRectangle":{"y":424.76474761962891,"x":474.96033501625061,"width":107.26499999999999,"height":16.580001831054688}},{"text":"2","targetRectangle":{"y":503.27999913692474,"x":1790.1941507160664,"width":11.119999999999891,"height":23.44000244140625}},{"text":"all","targetRectangle":{"y":424.76474761962891,"x":382.61170783638954,"width":14.714999999999975,"height":16.580001831054688}},{"text":"music_circle.png","targetRectangle":{"y":91.423728942871094,"x":920,"width":80.000001192092896,"height":80.000001192092896}},{"text":"back.png","targetRectangle":{"y":991.47429509847643,"x":917.5283203125,"width":71.849595849298566,"height":70.000000279254891}},{"text":"also","targetRectangle":{"y":706.76474761962891,"x":868.91918694972992,"width":27.495000000000005,"height":16.580001831054688}},{"text":"3","targetRectangle":{"y":765.53549230098724,"x":1790.1941507160664,"width":11.119999999999891,"height":23.44000244140625}},{"text":"grass","targetRectangle":{"y":556.48880767822266,"x":1504.6699994802475,"width":36.660000000000082,"height":16.580001831054688}},{"text":"days","targetRectangle":{"y":424.76474761962891,"x":288.98419785499573,"width":31.949999999999989,"height":16.580001831054688}},{"text":"for","targetRectangle":{"y":706.76474761962891,"x":792.97756123542786,"width":18.044999999999959,"height":16.580001831054688}},{"text":"He-lay down-me","targetRectangle":{"y":556.48880767822266,"x":1293.829124212265,"width":111.67499999999995,"height":16.580001831054688}},{"text":"x2","targetRectangle":{"y":487.33474767208099,"x":240.10138469934464,"width":21.480000000000018,"height":23.44000244140625}},{"text":"adapted to hebrew by S. Castillo, 2023, music by Phil Wickham, 2020 ","targetRectangle":{"y":193.44745779037476,"x":98.599999904632568,"width":1301.5949999999993,"height":53.694686889648438}},{"text":"my-life","targetRectangle":{"y":424.76474761962891,"x":202.82180881500244,"width":45.284999999999997,"height":16.580001831054688}}],"baseLayer":{"animations":[],"initialState":{"affineTransform":[1,0,0,1,0,0],"masksToBounds":false,"rotation":0,"scale":1,"position":{"pointX":960,"pointY":540},"width":1920,"sublayerTransform":[1,0,0,0,0,1,0,0,0,0,1,0,0,0,0,1],"contentsRect":{"y":0,"x":0,"width":1,"height":1},"opacity":1,"edgeAntialiasingMask":251658240,"height":1080,"hidden":false,"anchorPoint":{"pointX":0.5,"pointY":0.5}},"objectID":"0","layers":[{"animations":[],"initialState":{"affineTransform":[1,0,0,1,0,0],"masksToBounds":false,"rotation":0,"scale":1,"position":{"pointX":960,"pointY":540},"width":1920,"sublayerTransform":[1,0,0,0,0,1,0,0,0,0,1,-0.00035007912466775983,0,0,0,1],"contentsRect":{"y":0,"x":0,"width":1,"height":1},"opacity":1,"edgeAntialiasingMask":251658240,"height":1080,"hidden":false,"anchorPoint":{"pointX":0.5,"pointY":0.5}},"layers":[{"animations":[],"layers":[],"texturedRectangle":{"isBackgroundTexture":false,"singleTextureOpacity":1,"textureType":0,"textBaseline":0,"textXHeight":0,"isVerticalText":false},"initialState":{"affineTransform":[1,0,0,1,0,0],"masksToBounds":false,"rotation":0,"scale":1,"position":{"pointX":960,"pointY":540},"width":1920,"sublayerTransform":[1,0,0,0,0,1,0,0,0,0,1,0,0,0,0,1],"contentsRect":{"y":0,"x":0,"width":1,"height":1},"opacity":1,"edgeAntialiasingMask":0,"height":1080,"hidden":false,"anchorPoint":{"pointX":0.5,"pointY":0.5}},"texture":"263533AE3C29C0261D86F1C7013C5D9C"}]}]}}]}