{"assets":{"C3E2EC46ECF16EED03A997890ACB918D":{"type":"texture","index":2,"url":{"native":"assets\/180E25C3-B340-42FB-86A1-A1187FA78988.pdf"},"width":1920,"height":1080},"3E26B2F3E03492494493B9547701C2E7":{"type":"texture","index":0,"url":{"native":"assets\/180E25C3-B340-42FB-86A1-A1187FA78988.pdf"},"width":1920,"height":1080},"4CAB54AAB99FDD76B340666B12CDED53":{"type":"texture","index":1,"url":{"native":"assets\/180E25C3-B340-42FB-86A1-A1187FA78988.pdf"},"width":1920,"height":1080}},"events":[{"effects":[{"beginTime":0,"baseLayer":{"animations":[],"initialState":{"affineTransform":[1,0,0,1,0,0],"masksToBounds":false,"rotation":0,"scale":1,"position":{"pointX":960,"pointY":540},"width":1920,"sublayerTransform":[1,0,0,0,0,1,0,0,0,0,1,0,0,0,0,1],"contentsRect":{"y":0,"x":0,"width":1,"height":1},"opacity":1,"edgeAntialiasingMask":251658240,"height":1080,"hidden":false,"anchorPoint":{"pointX":0.5,"pointY":0.5}},"objectID":"0","layers":[{"animations":[],"initialState":{"affineTransform":[1,0,0,1,0,0],"masksToBounds":false,"rotation":0,"scale":1,"position":{"pointX":960,"pointY":540},"width":1920,"sublayerTransform":[1,0,0,0,0,1,0,0,0,0,1,-0.00035007912466775983,0,0,0,1],"contentsRect":{"y":0,"x":0,"width":1,"height":1},"opacity":1,"edgeAntialiasingMask":251658240,"height":1080,"hidden":false,"anchorPoint":{"pointX":0.5,"pointY":0.5}},"layers":[{"animations":[],"layers":[],"texturedRectangle":{"isBackgroundTexture":false,"singleTextureOpacity":1,"textureType":0,"textBaseline":0,"textXHeight":0,"isVerticalText":false},"initialState":{"affineTransform":[1,0,0,1,0,0],"masksToBounds":false,"rotation":0,"scale":1,"position":{"pointX":960,"pointY":540},"width":1920,"sublayerTransform":[1,0,0,0,0,1,0,0,0,0,1,0,0,0,0,1],"contentsRect":{"y":0,"x":0,"width":1,"height":1},"opacity":1,"edgeAntialiasingMask":0,"height":1080,"hidden":false,"anchorPoint":{"pointX":0.5,"pointY":0.5}},"texture":"4CAB54AAB99FDD76B340666B12CDED53"},{"animations":[{"additive":false,"timeOffset":0,"beginTime":0,"from":{"scalar":false},"repeatCount":0,"fillMode":"both","duration":0.001,"autoreverses":false,"property":"hidden","to":{"scalar":true},"removedOnCompletion":false}],"layers":[],"texturedRectangle":{"isBackgroundTexture":false,"singleTextureOpacity":1,"textureType":0,"textBaseline":0,"textXHeight":0,"isVerticalText":false},"initialState":{"affineTransform":[1,0,0,1,0,0],"masksToBounds":false,"rotation":0,"scale":1,"position":{"pointX":960,"pointY":540},"width":1920,"sublayerTransform":[1,0,0,0,0,1,0,0,0,0,1,0,0,0,0,1],"contentsRect":{"y":0,"x":0,"width":1,"height":1},"opacity":1,"edgeAntialiasingMask":0,"height":1080,"hidden":false,"anchorPoint":{"pointX":0.5,"pointY":0.5}},"texture":"3E26B2F3E03492494493B9547701C2E7"}]}]},"effects":[],"duration":0.001,"type":"transition","attributes":{"direction":0},"name":"none","objectID":"0"}],"automaticPlay":false,"hyperlinks":[{"url":"?slideid=73527225-8249-497D-A8A8-0535154E6893","events":{"73527225-8249-497D-A8A8-0535154E6893":{"effects":[{"beginTime":0,"baseLayer":{"animations":[],"initialState":{"affineTransform":[1,0,0,1,0,0],"masksToBounds":false,"rotation":0,"scale":1,"position":{"pointX":960,"pointY":540},"width":1920,"sublayerTransform":[1,0,0,0,0,1,0,0,0,0,1,0,0,0,0,1],"contentsRect":{"y":0,"x":0,"width":1,"height":1},"opacity":1,"edgeAntialiasingMask":251658240,"height":1080,"hidden":false,"anchorPoint":{"pointX":0.5,"pointY":0.5}},"objectID":"0","layers":[{"animations":[],"initialState":{"affineTransform":[1,0,0,1,0,0],"masksToBounds":false,"rotation":0,"scale":1,"position":{"pointX":960,"pointY":540},"width":1920,"sublayerTransform":[1,0,0,0,0,1,0,0,0,0,1,-0.00035007912466775983,0,0,0,1],"contentsRect":{"y":0,"x":0,"width":1,"height":1},"opacity":1,"edgeAntialiasingMask":251658240,"height":1080,"hidden":false,"anchorPoint":{"pointX":0.5,"pointY":0.5}},"layers":[{"animations":[],"layers":[],"texturedRectangle":{"isBackgroundTexture":false,"singleTextureOpacity":1,"textureType":0,"textBaseline":0,"textXHeight":0,"isVerticalText":false},"initialState":{"affineTransform":[1,0,0,1,0,0],"masksToBounds":false,"rotation":0,"scale":1,"position":{"pointX":960,"pointY":540},"width":1920,"sublayerTransform":[1,0,0,0,0,1,0,0,0,0,1,0,0,0,0,1],"contentsRect":{"y":0,"x":0,"width":1,"height":1},"opacity":1,"edgeAntialiasingMask":0,"height":1080,"hidden":false,"anchorPoint":{"pointX":0.5,"pointY":0.5}},"texture":"C3E2EC46ECF16EED03A997890ACB918D"},{"animations":[{"additive":false,"timeOffset":0,"beginTime":0,"from":{"scalar":false},"repeatCount":0,"fillMode":"both","duration":0.001,"autoreverses":false,"property":"hidden","to":{"scalar":true},"removedOnCompletion":false}],"layers":[],"texturedRectangle":{"isBackgroundTexture":false,"singleTextureOpacity":1,"textureType":0,"textBaseline":0,"textXHeight":0,"isVerticalText":false},"initialState":{"affineTransform":[1,0,0,1,0,0],"masksToBounds":false,"rotation":0,"scale":1,"position":{"pointX":960,"pointY":540},"width":1920,"sublayerTransform":[1,0,0,0,0,1,0,0,0,0,1,0,0,0,0,1],"contentsRect":{"y":0,"x":0,"width":1,"height":1},"opacity":1,"edgeAntialiasingMask":0,"height":1080,"hidden":false,"anchorPoint":{"pointX":0.5,"pointY":0.5}},"texture":"3E26B2F3E03492494493B9547701C2E7"}]}]},"effects":[],"duration":0.001,"type":"transition","attributes":{"direction":0},"name":"none","objectID":"0"}],"automaticPlay":false,"hyperlinks":[],"accessibility":[],"baseLayer":{"animations":[],"initialState":{"affineTransform":[1,0,0,1,0,0],"masksToBounds":false,"rotation":0,"scale":1,"position":{"pointX":960,"pointY":540},"width":1920,"sublayerTransform":[1,0,0,0,0,1,0,0,0,0,1,0,0,0,0,1],"contentsRect":{"y":0,"x":0,"width":1,"height":1},"opacity":1,"edgeAntialiasingMask":251658240,"height":1080,"hidden":false,"anchorPoint":{"pointX":0.5,"pointY":0.5}},"objectID":"0","layers":[{"animations":[],"initialState":{"affineTransform":[1,0,0,1,0,0],"masksToBounds":false,"rotation":0,"scale":1,"position":{"pointX":960,"pointY":540},"width":1920,"sublayerTransform":[1,0,0,0,0,1,0,0,0,0,1,-0.00035007912466775983,0,0,0,1],"contentsRect":{"y":0,"x":0,"width":1,"height":1},"opacity":1,"edgeAntialiasingMask":251658240,"height":1080,"hidden":false,"anchorPoint":{"pointX":0.5,"pointY":0.5}},"layers":[{"animations":[],"layers":[],"texturedRectangle":{"isBackgroundTexture":false,"singleTextureOpacity":1,"textureType":0,"textBaseline":0,"textXHeight":0,"isVerticalText":false},"initialState":{"affineTransform":[1,0,0,1,0,0],"masksToBounds":false,"rotation":0,"scale":1,"position":{"pointX":960,"pointY":540},"width":1920,"sublayerTransform":[1,0,0,0,0,1,0,0,0,0,1,0,0,0,0,1],"contentsRect":{"y":0,"x":0,"width":1,"height":1},"opacity":1,"edgeAntialiasingMask":0,"height":1080,"hidden":false,"anchorPoint":{"pointX":0.5,"pointY":0.5}},"texture":"3E26B2F3E03492494493B9547701C2E7"}]}]}}},"targetRectangle":{"y":976.47430419921875,"x":903.4501953125,"width":100,"height":100}},{"url":"?slideid=73527225-8249-497D-A8A8-0535154E6893","events":{"73527225-8249-497D-A8A8-0535154E6893":{"effects":[{"beginTime":0,"baseLayer":{"animations":[],"initialState":{"affineTransform":[1,0,0,1,0,0],"masksToBounds":false,"rotation":0,"scale":1,"position":{"pointX":960,"pointY":540},"width":1920,"sublayerTransform":[1,0,0,0,0,1,0,0,0,0,1,0,0,0,0,1],"contentsRect":{"y":0,"x":0,"width":1,"height":1},"opacity":1,"edgeAntialiasingMask":251658240,"height":1080,"hidden":false,"anchorPoint":{"pointX":0.5,"pointY":0.5}},"objectID":"0","layers":[{"animations":[],"initialState":{"affineTransform":[1,0,0,1,0,0],"masksToBounds":false,"rotation":0,"scale":1,"position":{"pointX":960,"pointY":540},"width":1920,"sublayerTransform":[1,0,0,0,0,1,0,0,0,0,1,-0.00035007912466775983,0,0,0,1],"contentsRect":{"y":0,"x":0,"width":1,"height":1},"opacity":1,"edgeAntialiasingMask":251658240,"height":1080,"hidden":false,"anchorPoint":{"pointX":0.5,"pointY":0.5}},"layers":[{"animations":[],"layers":[],"texturedRectangle":{"isBackgroundTexture":false,"singleTextureOpacity":1,"textureType":0,"textBaseline":0,"textXHeight":0,"isVerticalText":false},"initialState":{"affineTransform":[1,0,0,1,0,0],"masksToBounds":false,"rotation":0,"scale":1,"position":{"pointX":960,"pointY":540},"width":1920,"sublayerTransform":[1,0,0,0,0,1,0,0,0,0,1,0,0,0,0,1],"contentsRect":{"y":0,"x":0,"width":1,"height":1},"opacity":1,"edgeAntialiasingMask":0,"height":1080,"hidden":false,"anchorPoint":{"pointX":0.5,"pointY":0.5}},"texture":"C3E2EC46ECF16EED03A997890ACB918D"},{"animations":[{"additive":false,"timeOffset":0,"beginTime":0,"from":{"scalar":false},"repeatCount":0,"fillMode":"both","duration":0.001,"autoreverses":false,"property":"hidden","to":{"scalar":true},"removedOnCompletion":false}],"layers":[],"texturedRectangle":{"isBackgroundTexture":false,"singleTextureOpacity":1,"textureType":0,"textBaseline":0,"textXHeight":0,"isVerticalText":false},"initialState":{"affineTransform":[1,0,0,1,0,0],"masksToBounds":false,"rotation":0,"scale":1,"position":{"pointX":960,"pointY":540},"width":1920,"sublayerTransform":[1,0,0,0,0,1,0,0,0,0,1,0,0,0,0,1],"contentsRect":{"y":0,"x":0,"width":1,"height":1},"opacity":1,"edgeAntialiasingMask":0,"height":1080,"hidden":false,"anchorPoint":{"pointX":0.5,"pointY":0.5}},"texture":"3E26B2F3E03492494493B9547701C2E7"}]}]},"effects":[],"duration":0.001,"type":"transition","attributes":{"direction":0},"name":"none","objectID":"0"}],"automaticPlay":false,"hyperlinks":[],"accessibility":[],"baseLayer":{"animations":[],"initialState":{"affineTransform":[1,0,0,1,0,0],"masksToBounds":false,"rotation":0,"scale":1,"position":{"pointX":960,"pointY":540},"width":1920,"sublayerTransform":[1,0,0,0,0,1,0,0,0,0,1,0,0,0,0,1],"contentsRect":{"y":0,"x":0,"width":1,"height":1},"opacity":1,"edgeAntialiasingMask":251658240,"height":1080,"hidden":false,"anchorPoint":{"pointX":0.5,"pointY":0.5}},"objectID":"0","layers":[{"animations":[],"initialState":{"affineTransform":[1,0,0,1,0,0],"masksToBounds":false,"rotation":0,"scale":1,"position":{"pointX":960,"pointY":540},"width":1920,"sublayerTransform":[1,0,0,0,0,1,0,0,0,0,1,-0.00035007912466775983,0,0,0,1],"contentsRect":{"y":0,"x":0,"width":1,"height":1},"opacity":1,"edgeAntialiasingMask":251658240,"height":1080,"hidden":false,"anchorPoint":{"pointX":0.5,"pointY":0.5}},"layers":[{"animations":[],"layers":[],"texturedRectangle":{"isBackgroundTexture":false,"singleTextureOpacity":1,"textureType":0,"textBaseline":0,"textXHeight":0,"isVerticalText":false},"initialState":{"affineTransform":[1,0,0,1,0,0],"masksToBounds":false,"rotation":0,"scale":1,"position":{"pointX":960,"pointY":540},"width":1920,"sublayerTransform":[1,0,0,0,0,1,0,0,0,0,1,0,0,0,0,1],"contentsRect":{"y":0,"x":0,"width":1,"height":1},"opacity":1,"edgeAntialiasingMask":0,"height":1080,"hidden":false,"anchorPoint":{"pointX":0.5,"pointY":0.5}},"texture":"3E26B2F3E03492494493B9547701C2E7"}]}]}}},"targetRectangle":{"y":991.47429509847643,"x":917.5283203125,"width":71.849595849298566,"height":70.000000279254891}},{"url":"https:\/\/www.biblegateway.com\/passage\/?search=1+Chronicles+16:25;+Psalm+18:3;+95:3;+104:1;+147:5;+Jeremiah+10:6;+Philippians+2:9-11;&version=ESV","targetRectangle":{"y":70.619542598724365,"x":1557.2074604492188,"width":286.77600000000007,"height":115.3280029296875}},{"url":"https:\/\/audio.com\/stefaniecg\/audio\/gadol-elohai","targetRectangle":{"y":91.423728942871094,"x":913.453125,"width":80.000001192092896,"height":80.000001192092896}}],"accessibility":[{"text":"God-my great for","targetRectangle":{"y":760.52777105569839,"x":140.10208582878113,"width":184.92000000000002,"height":28.3280029296875}},{"text":"Gadol Elohai","targetRectangle":{"y":79,"x":99,"width":494.10500041797764,"height":100.53440856933594}},{"text":"[A]","targetRectangle":{"y":307.580810546875,"x":1693.4396240234375,"width":58.299999999999955,"height":58.600006103515625}},{"text":"גָּד֣וֹל אֱלֹהַ֥י","targetRectangle":{"y":428.580810546875,"x":1464.4739990234375,"width":287.265625,"height":81}},{"text":"שִׁיר֣וֹ","targetRectangle":{"y":529.580810546875,"x":1617.8333740234375,"width":133.90625,"height":81}},{"text":"כִּי גָּד֣וֹל אֱלֹהַ֥י ","targetRectangle":{"y":630.580810546875,"x":1384.2786865234375,"width":389.1015625,"height":81}},{"text":"כָּל אֶחָֽד יִרְאֶה","targetRectangle":{"y":731.580810546875,"x":1354.2396240234375,"width":397.5,"height":81}},{"text":"כִּי גָּד֣וֹל אֱלֹהַ֥י","targetRectangle":{"y":832.580810546875,"x":1384.2786865234375,"width":367.4609375,"height":81}},{"text":"my-God great","targetRectangle":{"y":461.72494512796402,"x":1150.0743279457092,"width":149.37599999999998,"height":28.3280029296875}},{"text":"[Bridge]","targetRectangle":{"y":307.580810546875,"x":788.38981201171873,"width":138.48000000000002,"height":46.8800048828125}},{"text":"שֵׁם מְעַל כָּל שֵׁם","targetRectangle":{"y":416.580810546875,"x":469.52606201171875,"width":457.34375,"height":81}},{"text":"אוֹתְךָ רָאוּי לְהַלֵּ֔ל","targetRectangle":{"y":517.580810546875,"x":455.85418701171875,"width":471.015625,"height":81}},{"text":"ליבי יָשִֽׁיר ","targetRectangle":{"y":618.580810546875,"x":657.57293701171875,"width":290.9375,"height":81}},{"text":"כִּי גָּד֣וֹל אֱלֹהַ֥י ","targetRectangle":{"y":719.580810546875,"x":559.40887451171875,"width":389.1015625,"height":81}},{"text":"[A] x1","targetRectangle":{"y":857.580810546875,"x":811.70981201171878,"width":115.15999999999997,"height":59.600006103515625}},{"text":"sing","targetRectangle":{"y":554.94061285257339,"x":1202.5383303165436,"width":44.448000000000093,"height":28.3280029296875}},{"text":"by Joshua Aaron, 2012","targetRectangle":{"y":180.44745779037476,"x":98.599999904632568,"width":484.37999999999988,"height":53.694686889648438}},{"text":"name all above name","targetRectangle":{"y":438.41177374124527,"x":118.29809284210205,"width":228.52800000000002,"height":28.3280029296875}},{"text":"my-God great for","targetRectangle":{"y":661.57427984476089,"x":1132.3023269176483,"width":184.92000000000007,"height":28.3280029296875}},{"text":"back.png","targetRectangle":{"y":991.47429509847643,"x":917.5283203125,"width":71.849595849298566,"height":70.000000279254891}},{"text":"praise-to worthy (<-obj)","targetRectangle":{"y":532.79797369241714,"x":106.70608615875244,"width":251.71200000000005,"height":28.3280029296875}},{"text":"will-see one all","targetRectangle":{"y":760.52777105569839,"x":1145.6703314781189,"width":158.18399999999997,"height":28.3280029296875}},{"text":"￼","targetRectangle":{"y":1022.4577338695526,"x":1856.1666821769322,"width":20.016000000000076,"height":21.496002197265625}},{"text":"sing-will-he heart-my","targetRectangle":{"y":639.18408209085464,"x":119.22208404541016,"width":226.68000000000006,"height":28.3280029296875}},{"text":"my-God great for","targetRectangle":{"y":861.42358404397964,"x":1132.3023269176483,"width":184.92000000000007,"height":28.3280029296875}},{"text":"Scripture reference:\\u20281 Chronicles 16:25; Psalm 18:3; 95:3; 104:1; 147:5; Jeremiah 10:6; Philippians 2:9-11;","targetRectangle":{"y":41.619542598724365,"x":1557.2074604492188,"width":286.77600000000007,"height":144.3280029296875}},{"text":"music_circle.png","targetRectangle":{"y":91.423728942871094,"x":913.453125,"width":80.000001192092896,"height":80.000001192092896}}],"baseLayer":{"animations":[],"initialState":{"affineTransform":[1,0,0,1,0,0],"masksToBounds":false,"rotation":0,"scale":1,"position":{"pointX":960,"pointY":540},"width":1920,"sublayerTransform":[1,0,0,0,0,1,0,0,0,0,1,0,0,0,0,1],"contentsRect":{"y":0,"x":0,"width":1,"height":1},"opacity":1,"edgeAntialiasingMask":251658240,"height":1080,"hidden":false,"anchorPoint":{"pointX":0.5,"pointY":0.5}},"objectID":"0","layers":[{"animations":[],"initialState":{"affineTransform":[1,0,0,1,0,0],"masksToBounds":false,"rotation":0,"scale":1,"position":{"pointX":960,"pointY":540},"width":1920,"sublayerTransform":[1,0,0,0,0,1,0,0,0,0,1,-0.00035007912466775983,0,0,0,1],"contentsRect":{"y":0,"x":0,"width":1,"height":1},"opacity":1,"edgeAntialiasingMask":251658240,"height":1080,"hidden":false,"anchorPoint":{"pointX":0.5,"pointY":0.5}},"layers":[{"animations":[],"layers":[],"texturedRectangle":{"isBackgroundTexture":false,"singleTextureOpacity":1,"textureType":0,"textBaseline":0,"textXHeight":0,"isVerticalText":false},"initialState":{"affineTransform":[1,0,0,1,0,0],"masksToBounds":false,"rotation":0,"scale":1,"position":{"pointX":960,"pointY":540},"width":1920,"sublayerTransform":[1,0,0,0,0,1,0,0,0,0,1,0,0,0,0,1],"contentsRect":{"y":0,"x":0,"width":1,"height":1},"opacity":1,"edgeAntialiasingMask":0,"height":1080,"hidden":false,"anchorPoint":{"pointX":0.5,"pointY":0.5}},"texture":"3E26B2F3E03492494493B9547701C2E7"}]}]}}]}